pandatex.py
utils/_texbasics.py
utils/_validate.py
PandaTex-1.0.0.dist-info/LICENSE
PandaTex-1.0.0.dist-info/METADATA
PandaTex-1.0.0.dist-info/WHEEL
PandaTex-1.0.0.dist-info/top_level.txt
PandaTex-1.0.0.dist-info/RECORD
