Metadata-Version: 2.1
Name: PandaTex
Version: 1.0.0
Summary: PandaTex is a package to transform Pandas data tables into .tex files
Home-page: https://github.com/Marcelo-Kenji-Noda/PandaTexModule
Author: Marcelo Kenji Noda
Author-email: nodamarcelokenjinoda@gmail.com
License: UNKNOWN
Platform: UNKNOWN
Classifier: Programming Language :: Python :: 3.7
License-File: LICENSE
Requires-Dist: pandas
Requires-Dist: numpy
Provides-Extra: dev
Requires-Dist: pytest (>=3.7) ; extra == 'dev'
